{
    "produits": [
        {
            "index": "1394",
            "upc": "0",
            "asin": "B079669VHB",
            "product_name": "Everpro",
            "brand": "Everpro",
            "image_link": "https://m.media-amazon.com/images/I/61IKSkskmUL.jpg",
            "price": "8.97",
            "list_of_ingredients": "[]",
            "cas_list": "[]",
            "score": "[]",
            "cas_score": "[]",
            "certifications": "[]",
            "category": "Hair Care",
            "subcategory": "Hair Coloring Products",
            "recommended_product": "No",
            "recommandation_rank": "0",
            "p_category": "0",
            "p_subcategory": "0",
            "seller": "Amazon",
            "affiliation_link": "http://www.amazon.com/dp/B079669VHB/ref=nosim?tag=tera042-20",
            "amazon_url": "https://www.amazon.com/Gray-Away-Womens-Everpro-Quick/dp/B079669VHB/ref=zg_bs_10728531_77?_encoding=UTF8&psc=1&refRID=66PAS5XA38HTJEXKRM7R",
            "source": "Ulta",
            "overall_score": "Orange",
            "sku": "GG8",
            "category_id": "1",
            "affiliation_website":"amazon.com",
            "manufacturing_country":  "USA",
            "certifications": "[]",
            "values": "[]",
            "description":"Lorem ipsum dolor",
            "short_description": "Lorem ipsum dolor",
            "products_gallery":"[]",
            "video": "",
            "related_products":"",
            "amazon_reviews": "",
            "url_key":"everpro",
            "echa_list": "[]",
            "ingredients_score": "[]"
        }
    ]
}
